a2b/__init__.py
a2b/link_utils.py
a2b/main.py
a2b/markdown.py
a2b/message.py
a2b/notion.py
a2b/s2.py
a2b-1.0.7.dist-info/LICENSE
a2b-1.0.7.dist-info/METADATA
a2b-1.0.7.dist-info/WHEEL
a2b-1.0.7.dist-info/entry_points.txt
a2b-1.0.7.dist-info/top_level.txt
a2b-1.0.7.dist-info/RECORD
