Metadata-Version: 2.1
Name: a2b
Version: 1.0.7
Summary: Replace arxiv links in markdowns by their corresponding bibliography.
Home-page: https://github.com/kevinkevin556/a2b
Author: Zhen-Lun Hong
Author-email: kevink556@gmail.com
License: MIT
Keywords: arxiv,bibliography,markdown,Notion
Platform: UNKNOWN
Classifier: Programming Language :: Python :: 3
Classifier: Topic :: Education
Classifier: Topic :: Text Processing :: Markup :: Markdown
Classifier: Topic :: Utilities
Classifier: License :: OSI Approved :: MIT License
